pasargad/__init__.py
pasargad/analyzer.py
pasargad/challenge.py
pasargad/core.py
pasargad/detector.py
pasargad/firewall.py
pasargad/logger.py
pasargad/ratelimiter.py
pasargad/storage.py
pasargad-5.0.0.dist-info/METADATA
pasargad-5.0.0.dist-info/WHEEL
pasargad-5.0.0.dist-info/top_level.txt
pasargad-5.0.0.dist-info/RECORD
