Metadata-Version: 2.4
Name: pasargad
Version: 5.0.0
Summary: An ultra-strong DDoS and attack protection library
Home-page: https://github.com/pasargadcdn
Author: ramox
Author-email: actramox@gmail.com
Classifier: Programming Language :: Python :: 3
Classifier: License :: OSI Approved :: MIT License
Classifier: Operating System :: OS Independent
Requires-Python: >=3.6
Requires-Dist: scapy>=2.4.5
Requires-Dist: psutil>=5.9.0
Requires-Dist: numpy>=1.23.0
Requires-Dist: pandas>=1.5.0
Requires-Dist: redis>=4.0.0
Requires-Dist: scikit-learn>=1.0.0
Requires-Dist: requests>=2.28.0
Requires-Dist: maxminddb>=2.0.0
Dynamic: author
Dynamic: author-email
Dynamic: classifier
Dynamic: description
Dynamic: description-content-type
Dynamic: home-page
Dynamic: requires-dist
Dynamic: requires-python
Dynamic: summary
